{"_id":2807,"name":"Ceinture Meulante","lvl":"129","type":"Ceinture","imgUrl":"https://s.ankama.com/www/static.ankama.com/dofus/www/game/items/200/10051.png","url":"https://www.dofus.com/fr/mmorpg/encyclopedie/equipements/2807-ceinture-meulante","description":"C'est Bowisse le Cordonnier en personne, qui a conçu cette ceinture. Il l'a offerte à Brouce Boulgoure lorsque celui-ci a réussi à déraciner à mains nues le Chêne Mou, il y a de ça très longtemps.","stats":[{"Sagesse":{"from":"31","to":"50"}},{"Dommages":{"from":"5","to":"10"}},{"Initiative":{"from":"401","to":"600"}},{"Résistance Air":{"from":"11","to":"15"}},{"Vitalité":{"from":"151","to":"300"}},{"Résistance Eau":{"from":"11","to":"15"}},{"Résistance Feu":{"from":"11","to":"15"}},{"Résistance Terre":{"from":"11","to":"15"}}],"condition":[],"recipe":[{"Queue du Mulou":{"id":"438","url":"https://www.dofus-touch.com/fr/mmorpg/encyclopedie/ressources/438-queue-mulou","imgUrl":"https://s.ankama.com/www/static.ankama.com/dofus/www/game/items/52/65105.w48h48.png","type":"Queue","lvl":"96","quantity":"20"}},{"Griffe de Muloubard":{"id":"440","url":"https://www.dofus-touch.com/fr/mmorpg/encyclopedie/ressources/440-griffe-muloubard","imgUrl":"https://s.ankama.com/www/static.ankama.com/dofus/www/game/items/52/15107.w48h48.png","type":"Ressources diverses","lvl":"96","quantity":"10"}},{"Faux Visage de Choudini":{"id":"1691","url":"https://www.dofus-touch.com/fr/mmorpg/encyclopedie/ressources/1691-faux-visage-choudini","imgUrl":"https://s.ankama.com/www/static.ankama.com/dofus/www/game/items/52/15976.w48h48.png","type":"Vêtement","lvl":"90","quantity":"10"}},{"Étoffe de Choudini":{"id":"1696","url":"https://www.dofus-touch.com/fr/mmorpg/encyclopedie/ressources/1696-etoffe-choudini","imgUrl":"https://s.ankama.com/www/static.ankama.com/dofus/www/game/items/52/15975.w48h48.png","type":"Étoffe","lvl":"90","quantity":"1"}},{"Cuir de Porkass":{"id":"2275","url":"https://www.dofus-touch.com/fr/mmorpg/encyclopedie/ressources/2275-cuir-porkass","imgUrl":"https://s.ankama.com/www/static.ankama.com/dofus/www/game/items/52/56429.w48h48.png","type":"Cuir","lvl":"46","quantity":"30"}},{"Scalp de Meulou":{"id":"2577","url":"https://www.dofus-touch.com/fr/mmorpg/encyclopedie/ressources/2577-scalp-meulou","imgUrl":"https://s.ankama.com/www/static.ankama.com/dofus/www/game/items/52/15583.w48h48.png","type":"Ressources diverses","lvl":"100","quantity":"10"}},{"Testicules de Meulou":{"id":"2582","url":"https://www.dofus-touch.com/fr/mmorpg/encyclopedie/ressources/2582-testicules-meulou","imgUrl":"https://s.ankama.com/www/static.ankama.com/dofus/www/game/items/52/15588.w48h48.png","type":"Ressources diverses","lvl":"100","quantity":"1"}},{"Testicules Magiques du Meulou":{"id":"2806","url":"https://www.dofus-touch.com/fr/mmorpg/encyclopedie/ressources/2806-testicules-magiques-meulou","imgUrl":"https://s.ankama.com/www/static.ankama.com/dofus/www/game/items/52/15651.w48h48.png","type":"Ressources diverses","lvl":"100","quantity":"1"}}],"setId":0}