{"_id":6756,"name":"Kwape de Terre","lvl":"41","type":"Cape","imgUrl":"https://s.ankama.com/www/static.ankama.com/dofus/www/game/items/200/17064.png","url":"https://www.dofus.com/fr/mmorpg/encyclopedie/equipements/6756-kwape-terre","description":"Idéale pour se camoufler en motte de terre géante, cette cape vous permettra d'attaquer par surprise les laboureurs et leur voler leurs richesses. Elle est donc avant tout réservée aux collectionneurs de silex.","stats":[{"Force":{"from":"11","to":"15"}},{"Invocations":{"from":"1"}},{"Initiative":{"from":"21","to":"30"}},{"% Résistance Terre":{"from":"3","to":"5"}}],"condition":[],"recipe":[{"Ebonite":{"id":"746","url":"https://www.dofus-touch.com/fr/mmorpg/encyclopedie/ressources/746-ebonite","imgUrl":"https://s.ankama.com/www/static.ankama.com/dofus/www/game/items/52/40658.w48h48.png","type":"Alliage","lvl":"40","quantity":"2"}},{"Plume du Kwak de Terre":{"id":"1141","url":"https://www.dofus-touch.com/fr/mmorpg/encyclopedie/ressources/1141-plume-kwak-terre","imgUrl":"https://s.ankama.com/www/static.ankama.com/dofus/www/game/items/52/53223.w48h48.png","type":"Plume","lvl":"44","quantity":"6"}},{"Plume du Kwakwa":{"id":"12016","url":"https://www.dofus-touch.com/fr/mmorpg/encyclopedie/ressources/12016-plume-kwakwa","imgUrl":"https://s.ankama.com/www/static.ankama.com/dofus/www/game/items/52/53649.w48h48.png","type":"Plume","lvl":"60","quantity":"11"}},{"Lamelle de Champa Marron":{"id":"16166","url":"https://www.dofus-touch.com/fr/mmorpg/encyclopedie/ressources/16166-lamelle-champa-marron","imgUrl":"https://s.ankama.com/www/static.ankama.com/dofus/www/game/items/52/119011.w48h48.png","type":"Champignon","lvl":"39","quantity":"5"}}],"setId":14}