{"_id":8459,"name":"Collier Cérémonial du Seigneur des Rats","lvl":"134","type":"Amulette","imgUrl":"https://s.ankama.com/www/static.ankama.com/dofus/www/game/items/200/1117.png","url":"https://www.dofus.com/fr/mmorpg/encyclopedie/equipements/8459-collier-ceremonial-seigneur-rats","description":"Afin d'éviter qu'on le lui vole, ce collier est glissé autour du cou de l'héritier du Seigneur des rats à sa naissance. Ainsi, à l'âge adulte, le seul moyen de le lui enlever est de lui couper la tête. On le lui vole tout de même.","stats":[{"PA":{"from":"1"}},{"Agilité":{"from":"26","to":"40"}},{"Intelligence":{"from":"16","to":"30"}},{"Vitalité":{"from":"101","to":"150"}},{"Sagesse":{"from":"16","to":"25"}},{"Dommages":{"from":"6","to":"10"}},{"Initiative":{"from":"201","to":"400"}},{"Prospection":{"from":"11","to":"15"}},{"% Résistance Neutre":{"from":"6","to":"10"}}],"condition":[],"recipe":[{"Dent de Karne":{"id":"2259","url":"https://www.dofus-touch.com/fr/mmorpg/encyclopedie/ressources/2259-dent-karne","imgUrl":"https://s.ankama.com/www/static.ankama.com/dofus/www/game/items/52/47013.w48h48.png","type":"Os","lvl":"31","quantity":"100"}},{"Crocs de Rats":{"id":"2322","url":"https://www.dofus-touch.com/fr/mmorpg/encyclopedie/ressources/2322-crocs-rats","imgUrl":"https://s.ankama.com/www/static.ankama.com/dofus/www/game/items/52/47464.w48h48.png","type":"Os","lvl":"26","quantity":"50"}},{"Étoffe de Péki":{"id":"8380","url":"https://www.dofus-touch.com/fr/mmorpg/encyclopedie/ressources/8380-etoffe-peki","imgUrl":"https://s.ankama.com/www/static.ankama.com/dofus/www/game/items/52/55721.w48h48.png","type":"Étoffe","lvl":"140","quantity":"1"}},{"Collier du Rat Noir":{"id":"8445","url":"https://www.dofus-touch.com/fr/mmorpg/encyclopedie/equipements/8445-collier-rat-noir","imgUrl":"https://s.ankama.com/www/static.ankama.com/dofus/www/game/items/52/1115.w48h48.png","type":"Amulette","lvl":"103","quantity":"1"}},{"Collier du Rat Blanc":{"id":"8453","url":"https://www.dofus-touch.com/fr/mmorpg/encyclopedie/equipements/8453-collier-rat-blanc","imgUrl":"https://s.ankama.com/www/static.ankama.com/dofus/www/game/items/52/1116.w48h48.png","type":"Amulette","lvl":"102","quantity":"1"}},{"Poil de Rat d'Égoutant":{"id":"8481","url":"https://www.dofus-touch.com/fr/mmorpg/encyclopedie/ressources/8481-poil-rat-egoutant","imgUrl":"https://s.ankama.com/www/static.ankama.com/dofus/www/game/items/52/54670.w48h48.png","type":"Poil","lvl":"60","quantity":"100"}},{"Duvet de Tofoune":{"id":"8484","url":"https://www.dofus-touch.com/fr/mmorpg/encyclopedie/ressources/8484-duvet-tofoune","imgUrl":"https://s.ankama.com/www/static.ankama.com/dofus/www/game/items/52/54671.w48h48.png","type":"Poil","lvl":"36","quantity":"5"}},{"Fémur de Sphincter Cell":{"id":"8490","url":"https://www.dofus-touch.com/fr/mmorpg/encyclopedie/ressources/8490-femur-sphincter-cell","imgUrl":"https://s.ankama.com/www/static.ankama.com/dofus/www/game/items/52/47657.w48h48.png","type":"Os","lvl":"150","quantity":"5"}}],"setId":64}