{"_id":6916,"name":"Sac du Petit Moskito","lvl":"16","type":"Sac à dos","imgUrl":"https://s.ankama.com/www/static.ankama.com/dofus/www/game/items/200/81059.png","url":"https://www.dofus.com/fr/mmorpg/encyclopedie/equipements/6916-sac-petit-moskito","description":"Ce sac en peau et en ailes de Moskitos faisait jadis fureur à la sortie des écoles. Aujourd'hui, il est totalement démodé, et a été remplacé dans le cœur des enfants par le Petit sac d'écolier du Chef Crocodaille. Du grand n'importe quoi, quand on voit que ce dernier est largement plus cher, et surtout beaucoup plus laid. Une sombre histoire de mode.","stats":[{"Pods":{"from":"71","to":"100"}},{"Chance":{"from":"11","to":"15"}}],"condition":[],"recipe":[{"Ailes de Moskito":{"id":"307","url":"https://www.dofus-touch.com/fr/mmorpg/encyclopedie/ressources/307-ailes-moskito","imgUrl":"https://s.ankama.com/www/static.ankama.com/dofus/www/game/items/52/104019.w48h48.png","type":"Aile","lvl":"18","quantity":"4"}},{"Pétale Magique du Tournesol Affamé":{"id":"8157","url":"https://www.dofus-touch.com/fr/mmorpg/encyclopedie/ressources/8157-petale-magique-tournesol-affame","imgUrl":"https://s.ankama.com/www/static.ankama.com/dofus/www/game/items/52/35002.w48h48.png","type":"Fleur","lvl":"20","quantity":"1"}},{"Bois Vermoulu":{"id":"16487","url":"https://www.dofus-touch.com/fr/mmorpg/encyclopedie/ressources/16487-bois-vermoulu","imgUrl":"https://s.ankama.com/www/static.ankama.com/dofus/www/game/items/52/38683.w48h48.png","type":"Bois","lvl":"18","quantity":"1"}}],"setId":23}