{"_id":698,"name":"Choipo Podlard","lvl":"33","type":"Chapeau","imgUrl":"https://s.ankama.com/www/static.ankama.com/dofus/www/game/items/200/16004.png","url":"https://www.dofus.com/fr/mmorpg/encyclopedie/equipements/698-choipo-podlard","description":"Le Choipo Podlard vient d'une grande école de magie. Créature vivante, il a rencontré les plus grands magiciens de notre temps, tels que Mme Magoa AlaGale, Mr Doublegore et le célèbre Remy Krokeur.","stats":[{"Force":{"from":"-20"}},{"Intelligence":{"from":"-20"}},{"Agilité":{"from":"-20"}},{"Chance":{"from":"-20"}},{"Portée":{"from":"2"}}],"condition":[],"recipe":[{"Défense du Sanglier":{"id":"387","url":"https://www.dofus-touch.com/fr/mmorpg/encyclopedie/ressources/387-defense-sanglier","imgUrl":"https://s.ankama.com/www/static.ankama.com/dofus/www/game/items/52/47059.w48h48.png","type":"Os","lvl":"24","quantity":"5"}},{"Laine du Chef de Guerre Bouftou":{"id":"882","url":"https://www.dofus-touch.com/fr/mmorpg/encyclopedie/ressources/882-laine-chef-guerre-bouftou","imgUrl":"https://s.ankama.com/www/static.ankama.com/dofus/www/game/items/52/57209.w48h48.png","type":"Laine","lvl":"29","quantity":"4"}},{"Pétale de Rose Obscure":{"id":"6842","url":"https://www.dofus-touch.com/fr/mmorpg/encyclopedie/ressources/6842-petale-rose-obscure","imgUrl":"https://s.ankama.com/www/static.ankama.com/dofus/www/game/items/52/25153.w48h48.png","type":"Fleur","lvl":"23","quantity":"5"}}],"setId":0}