{"_id":17449,"name":"Cape Rimordiale","lvl":"80","type":"Cape","imgUrl":"https://s.ankama.com/www/static.ankama.com/dofus/www/game/items/200/17359.png","url":"https://www.dofus.com/fr/mmorpg/encyclopedie/equipements/17449-cape-rimordiale","description":"Traditionnellement revêtue lors de cérémonies et de voyages, cette cape est imprégnée d’une puissante magie qui donne à son porteur un charisme incroyable, une attitude héroïque, et une protection à toute épreuve contre la pluie et les éclats de boue.","stats":[{"Augmente la portée du sort Drain Élémentaire de 2":{"from":"2"}},{"Réduit de le délai de relance du sort Lame Astrale":{"from":"1"}},{"15% Critique sur le sort Glacier":{"from":"15"}},{"Désactive la ligne de vue du sort Propagation":{}},{"15% Critique sur le sort Morph":{"from":"15"}},{"Augmente de le nombre de lancer maximal par tour du sort Piège Élémentaire":{"from":"1"}},{"15% Critique sur le sort Lame Tellurique":{"from":"15"}},{"Augmente la portée du sort Stalactite de 1":{"from":"1"}}],"condition":[],"recipe":[{"Patte d'Arakne des Égouts":{"id":"2451","url":"https://www.dofus-touch.com/fr/mmorpg/encyclopedie/ressources/2451-patte-arakne-egouts","imgUrl":"https://s.ankama.com/www/static.ankama.com/dofus/www/game/items/52/25159.w48h48.png","type":"Patte","lvl":"26","quantity":"1"}},{"Maillot de corps de Barbroussa":{"id":"8757","url":"https://www.dofus-touch.com/fr/mmorpg/encyclopedie/ressources/8757-maillot-corps-barbroussa","imgUrl":"https://s.ankama.com/www/static.ankama.com/dofus/www/game/items/52/15011.w48h48.png","type":"Vêtement","lvl":"64","quantity":"4"}},{"Foulard du Sparo":{"id":"8760","url":"https://www.dofus-touch.com/fr/mmorpg/encyclopedie/ressources/8760-foulard-sparo","imgUrl":"https://s.ankama.com/www/static.ankama.com/dofus/www/game/items/52/15014.w48h48.png","type":"Vêtement","lvl":"63","quantity":"4"}},{"Plume de fesse du Kido":{"id":"8766","url":"https://www.dofus-touch.com/fr/mmorpg/encyclopedie/ressources/8766-plume-fesse-kido","imgUrl":"https://s.ankama.com/www/static.ankama.com/dofus/www/game/items/52/53005.w48h48.png","type":"Plume","lvl":"101","quantity":"10"}},{"Aile du Bitouf des Plaines":{"id":"8767","url":"https://www.dofus-touch.com/fr/mmorpg/encyclopedie/ressources/8767-aile-bitouf-plaines","imgUrl":"https://s.ankama.com/www/static.ankama.com/dofus/www/game/items/52/104001.w48h48.png","type":"Aile","lvl":"103","quantity":"10"}},{"Étoffe de Ouassingue":{"id":"8801","url":"https://www.dofus-touch.com/fr/mmorpg/encyclopedie/ressources/8801-etoffe-ouassingue","imgUrl":"https://s.ankama.com/www/static.ankama.com/dofus/www/game/items/52/55018.w48h48.png","type":"Étoffe","lvl":"36","quantity":"20"}},{"Étoffe de Gourlo le Terrible":{"id":"8995","url":"https://www.dofus-touch.com/fr/mmorpg/encyclopedie/ressources/8995-etoffe-gourlo-terrible","imgUrl":"https://s.ankama.com/www/static.ankama.com/dofus/www/game/items/52/55729.w48h48.png","type":"Étoffe","lvl":"70","quantity":"1"}}],"setId":392}