{"_id":12058,"name":"Chapeaudron","lvl":"1","type":"Objet d'apparat","imgUrl":"https://s.ankama.com/www/static.ankama.com/dofus/www/game/items/200/16301.png","url":"https://www.dofus.com/fr/mmorpg/encyclopedie/equipements/12058-chapeaudron","description":"Affublé de cet étrange chapeau, il vous prendra une fantaisiste envie de vous rendre à une Taverne en titubant, demandant alors à boire de l'Hydre au miel et à manger du sang lié. Un peu comme d'habitude, finalement. Déposez ce chapeau sur un autre chapeau déjà équipé pour lui transmettre son apparence","stats":[{"Compatible avec : 0":{"from":"0"}}],"condition":[],"recipe":[],"setId":0}