{"_id":15189,"name":"Amulette du Piloztère","lvl":"200","type":"Amulette","imgUrl":"https://s.ankama.com/www/static.ankama.com/dofus/www/game/items/200/1252.png","url":"https://www.dofus.com/fr/mmorpg/encyclopedie/equipements/15189-amulette-piloztere","description":"Cette amulette sert à contrôler la pureté de l’âme de son porteur : les deux boules remontent à chaque fois que vous avez une pensée malsaine, jusqu’à l’étranglement. En général, ce n’est qu’une question de temps.","stats":[{"Vitalité":{"from":"301","to":"350"}},{"Force":{"from":"51","to":"70"}},{"Chance":{"from":"51","to":"70"}},{"Résistance Poussée":{"from":"-21","to":"-30"}},{"Résistance Critiques":{"from":"21","to":"30"}},{"Sagesse":{"from":"31","to":"40"}},{"Prospection":{"from":"11","to":"15"}},{"Dommages Terre":{"from":"16","to":"20"}},{"Dommages Neutre":{"from":"16","to":"20"}},{"Dommages Eau":{"from":"16","to":"20"}},{"% Résistance Eau":{"from":"7","to":"10"}},{"Esquive PA":{"from":"16","to":"20"}},{"% Critique":{"from":"3","to":"4"}}],"condition":[],"recipe":[{"Sphénoïde du Kimbo":{"id":"13164","url":"https://www.dofus-touch.com/fr/mmorpg/encyclopedie/ressources/13164-sphenoide-kimbo","imgUrl":"https://s.ankama.com/www/static.ankama.com/dofus/www/game/items/52/47692.w48h48.png","type":"Os","lvl":"160","quantity":"11"}},{"Barbe de Merkator":{"id":"14864","url":"https://www.dofus-touch.com/fr/mmorpg/encyclopedie/ressources/14864-barbe-merkator","imgUrl":"https://s.ankama.com/www/static.ankama.com/dofus/www/game/items/52/54696.w48h48.png","type":"Poil","lvl":"200","quantity":"9"}},{"Joyau de la couronne du roi Nidas":{"id":"15176","url":"https://www.dofus-touch.com/fr/mmorpg/encyclopedie/ressources/15176-joyau-couronne-roi-nidas","imgUrl":"https://s.ankama.com/www/static.ankama.com/dofus/www/game/items/52/15875.w48h48.png","type":"Pierre précieuse","lvl":"200","quantity":"11"}},{"Sourcil de Barbétoal":{"id":"15178","url":"https://www.dofus-touch.com/fr/mmorpg/encyclopedie/ressources/15178-sourcil-barbetoal","imgUrl":"https://s.ankama.com/www/static.ankama.com/dofus/www/game/items/52/15877.w48h48.png","type":"Poil","lvl":"200","quantity":"33"}},{"Dent de Lévitrof":{"id":"15179","url":"https://www.dofus-touch.com/fr/mmorpg/encyclopedie/ressources/15179-dent-levitrof","imgUrl":"https://s.ankama.com/www/static.ankama.com/dofus/www/game/items/52/15878.w48h48.png","type":"Os","lvl":"200","quantity":"34"}},{"Kamatrix":{"id":"15182","url":"https://www.dofus-touch.com/fr/mmorpg/encyclopedie/ressources/15182-kamatrix","imgUrl":"https://s.ankama.com/www/static.ankama.com/dofus/www/game/items/52/15881.w48h48.png","type":"Ressources diverses","lvl":"100","quantity":"15"}},{"Trame Dimensionnelle":{"id":"15219","url":"https://www.dofus-touch.com/fr/mmorpg/encyclopedie/ressources/15219-trame-dimensionnelle","imgUrl":"https://s.ankama.com/www/static.ankama.com/dofus/www/game/items/52/59642.w48h48.png","type":"Étoffe","lvl":"100","quantity":"15"}},{"Tourmaline":{"id":"15271","url":"https://www.dofus-touch.com/fr/mmorpg/encyclopedie/ressources/15271-tourmaline","imgUrl":"https://s.ankama.com/www/static.ankama.com/dofus/www/game/items/52/50719.w48h48.png","type":"Pierre précieuse","lvl":"10","quantity":"15"}}],"setId":332}