{"_id":1476,"name":"Amulette du Craqueleur","lvl":"47","type":"Amulette","imgUrl":"https://s.ankama.com/www/static.ankama.com/dofus/www/game/items/200/1025.png","url":"https://www.dofus.com/fr/mmorpg/encyclopedie/equipements/1476-amulette-craqueleur","description":"Cette puissante amulette contient toute la vie du Craqueleur, tous les objets qu'il a récoltés avant de mourir sous les coups de butoir d'aventuriers attirés par ses richesses.","stats":[{"Vitalité":{"from":"21","to":"25"}},{"Force":{"from":"21","to":"25"}},{"Intelligence":{"from":"21","to":"25"}},{"Agilité":{"from":"21","to":"25"}},{"Dommages":{"from":"2","to":"3"}}],"condition":[],"recipe":[{"Ebonite":{"id":"746","url":"https://www.dofus-touch.com/fr/mmorpg/encyclopedie/ressources/746-ebonite","imgUrl":"https://s.ankama.com/www/static.ankama.com/dofus/www/game/items/52/40658.w48h48.png","type":"Alliage","lvl":"40","quantity":"2"}},{"Cœur de Craqueleur":{"id":"2306","url":"https://www.dofus-touch.com/fr/mmorpg/encyclopedie/ressources/2306-coeur-craqueleur","imgUrl":"https://s.ankama.com/www/static.ankama.com/dofus/www/game/items/52/51456.w48h48.png","type":"Pierre brute","lvl":"61","quantity":"1"}},{"Fémur du Chafer Rōnin":{"id":"13096","url":"https://www.dofus-touch.com/fr/mmorpg/encyclopedie/ressources/13096-femur-chafer-rōnin","imgUrl":"https://s.ankama.com/www/static.ankama.com/dofus/www/game/items/52/47696.w48h48.png","type":"Os","lvl":"40","quantity":"10"}},{"Lamelle de Champa Vert":{"id":"16168","url":"https://www.dofus-touch.com/fr/mmorpg/encyclopedie/ressources/16168-lamelle-champa-vert","imgUrl":"https://s.ankama.com/www/static.ankama.com/dofus/www/game/items/52/119013.w48h48.png","type":"Champignon","lvl":"39","quantity":"7"}}],"setId":0}