{"_id":15613,"name":"Casque Draconique","lvl":"1","type":"Objet d'apparat","imgUrl":"https://s.ankama.com/www/static.ankama.com/dofus/www/game/items/200/16446.png","url":"https://www.dofus.com/fr/mmorpg/encyclopedie/equipements/15613-casque-draconique","description":"Orné de cette corne, vous n'aurez plus peur de foncer tête baissée à la moindre menace : vous aurez même toutes les raisons de le faire. Déposez ce chapeau sur un autre chapeau déjà équipé pour lui transmettre son apparence","stats":[{"Compatible avec : 0":{"from":"0"}}],"condition":[],"recipe":[],"setId":0}