{"_id":6731,"name":"Amukwak de Glace","lvl":"42","type":"Amulette","imgUrl":"https://s.ankama.com/www/static.ankama.com/dofus/www/game/items/200/1071.png","url":"https://www.dofus.com/fr/mmorpg/encyclopedie/equipements/6731-amukwak-glace","description":"Avec cette amulette autour du cou, vous pourriez tenter de faire croire à votre entourage que vous avez une haleine fraîche. Laissez tomber, c'est peine perdue.","stats":[{"Vitalité":{"from":"16","to":"20"}},{"Chance":{"from":"21","to":"30"}},{"% Résistance Eau":{"from":"4","to":"5"}},{"2% Critique":{"from":"2"}}],"condition":[],"recipe":[{"Bec du Kwak de Glace":{"id":"411","url":"https://www.dofus-touch.com/fr/mmorpg/encyclopedie/ressources/411-bec-kwak-glace","imgUrl":"https://s.ankama.com/www/static.ankama.com/dofus/www/game/items/52/47133.w48h48.png","type":"Os","lvl":"44","quantity":"2"}},{"Ebonite":{"id":"746","url":"https://www.dofus-touch.com/fr/mmorpg/encyclopedie/ressources/746-ebonite","imgUrl":"https://s.ankama.com/www/static.ankama.com/dofus/www/game/items/52/40658.w48h48.png","type":"Alliage","lvl":"40","quantity":"2"}},{"Carapace de Scarafeuille Bleu":{"id":"2291","url":"https://www.dofus-touch.com/fr/mmorpg/encyclopedie/ressources/2291-carapace-scarafeuille-bleu","imgUrl":"https://s.ankama.com/www/static.ankama.com/dofus/www/game/items/52/107442.w48h48.png","type":"Carapace","lvl":"38","quantity":"7"}},{"Plume du Kwakwa":{"id":"12016","url":"https://www.dofus-touch.com/fr/mmorpg/encyclopedie/ressources/12016-plume-kwakwa","imgUrl":"https://s.ankama.com/www/static.ankama.com/dofus/www/game/items/52/53649.w48h48.png","type":"Plume","lvl":"60","quantity":"7"}}],"setId":13}