{"_id":11727,"name":"Cape Peupret","lvl":"182","type":"Cape","imgUrl":"https://s.ankama.com/www/static.ankama.com/dofus/www/game/items/200/17215.png","url":"https://www.dofus.com/fr/mmorpg/encyclopedie/equipements/11727-cape-peupret","description":"Cette création très approximative n'a aucune forme, pas la moindre esthétique et semble pouvoir tomber en lambeaux d'un moment à un autre, mais est pourtant très puissante. Ne dit-on pas que l'habit ne fait pas le moine ?","stats":[{"Vitalité":{"from":"151","to":"200"}},{"Sagesse":{"from":"31","to":"50"}},{"Puissance":{"from":"31","to":"50"}},{"% Critique":{"from":"1","to":"2"}},{"Portée":{"from":"1","to":"2"}},{"Initiative":{"from":"151","to":"250"}},{"Prospection":{"from":"16","to":"25"}},{"Dommages Neutre":{"from":"5","to":"7"}},{"Dommages Terre":{"from":"5","to":"7"}},{"Dommages Feu":{"from":"5","to":"7"}},{"Dommages Air":{"from":"5","to":"7"}},{"Dommages Eau":{"from":"5","to":"7"}},{"Résistance Neutre":{"from":"5","to":"7"}},{"% Résistance Neutre":{"from":"5","to":"7"}},{"Retrait PA":{"from":"5","to":"7"}},{"Esquive PA":{"from":"-5","to":"-7"}},{"Retrait PM":{"from":"5","to":"7"}},{"Esquive PM":{"from":"-5","to":"-7"}}],"condition":[],"recipe":[{"Volve de Fistulor":{"id":"11888","url":"https://www.dofus-touch.com/fr/mmorpg/encyclopedie/ressources/11888-volve-fistulor","imgUrl":"https://s.ankama.com/www/static.ankama.com/dofus/www/game/items/52/119002.w48h48.png","type":"Champignon","lvl":"180","quantity":"30"}},{"Écorce d'Abrazif":{"id":"11891","url":"https://www.dofus-touch.com/fr/mmorpg/encyclopedie/ressources/11891-ecorce-abrazif","imgUrl":"https://s.ankama.com/www/static.ankama.com/dofus/www/game/items/52/96668.w48h48.png","type":"Écorce","lvl":"180","quantity":"42"}},{"Lamelle de Mérulette":{"id":"11893","url":"https://www.dofus-touch.com/fr/mmorpg/encyclopedie/ressources/11893-lamelle-merulette","imgUrl":"https://s.ankama.com/www/static.ankama.com/dofus/www/game/items/52/119003.w48h48.png","type":"Champignon","lvl":"180","quantity":"32"}},{"Patte de Korriandre":{"id":"11895","url":"https://www.dofus-touch.com/fr/mmorpg/encyclopedie/ressources/11895-patte-korriandre","imgUrl":"https://s.ankama.com/www/static.ankama.com/dofus/www/game/items/52/103580.w48h48.png","type":"Patte","lvl":"180","quantity":"11"}},{"Œil de Korriandre":{"id":"11896","url":"https://www.dofus-touch.com/fr/mmorpg/encyclopedie/ressources/11896-oeil-korriandre","imgUrl":"https://s.ankama.com/www/static.ankama.com/dofus/www/game/items/52/109596.w48h48.png","type":"Œil","lvl":"180","quantity":"1"}},{"Galet brasillant":{"id":"12740","url":"https://www.dofus-touch.com/fr/mmorpg/encyclopedie/ressources/12740-galet-brasillant","imgUrl":"https://s.ankama.com/www/static.ankama.com/dofus/www/game/items/52/15289.w48h48.png","type":"Galet","lvl":"150","quantity":"2"}},{"Ongle du Bworker":{"id":"13157","url":"https://www.dofus-touch.com/fr/mmorpg/encyclopedie/ressources/13157-ongle-bworker","imgUrl":"https://s.ankama.com/www/static.ankama.com/dofus/www/game/items/52/47695.w48h48.png","type":"Os","lvl":"180","quantity":"9"}},{"Calice du Tynril":{"id":"13166","url":"https://www.dofus-touch.com/fr/mmorpg/encyclopedie/ressources/13166-calice-tynril","imgUrl":"https://s.ankama.com/www/static.ankama.com/dofus/www/game/items/52/35637.w48h48.png","type":"Fleur","lvl":"140","quantity":"13"}}],"setId":0}