{"_id":19585,"name":"Chaussures Ardentes","lvl":"200","type":"Bottes","imgUrl":"https://s.ankama.com/www/static.ankama.com/dofus/www/game/items/200/11332.png","url":"https://www.dofus.com/fr/mmorpg/encyclopedie/equipements/19585-chaussures-ardentes","description":"En plus d'avoir le feu aux fesses, vous aurez le feu aux pieds.","stats":[{"Vitalité":{"from":"301","to":"350"}},{"Intelligence":{"from":"61","to":"80"}},{"Sagesse":{"from":"31","to":"40"}},{"Prospection":{"from":"11","to":"15"}},{"Tacle":{"from":"5","to":"7"}},{"Dommages Feu":{"from":"11","to":"15"}},{"% Résistance Terre":{"from":"7","to":"10"}},{"% Résistance Air":{"from":"7","to":"10"}},{"Retrait PA":{"from":"4","to":"5"}},{"Soins":{"from":"9","to":"12"}},{"Invocations":{"from":"1"}},{"-10% Critique":{"from":"-10"}},{"PM":{"from":"1"}}],"condition":[],"recipe":[{"Galet brasillant":{"id":"12740","url":"https://www.dofus-touch.com/fr/mmorpg/encyclopedie/ressources/12740-galet-brasillant","imgUrl":"https://s.ankama.com/www/static.ankama.com/dofus/www/game/items/52/15289.w48h48.png","type":"Galet","lvl":"150","quantity":"3"}},{"Tourmaline":{"id":"15271","url":"https://www.dofus-touch.com/fr/mmorpg/encyclopedie/ressources/15271-tourmaline","imgUrl":"https://s.ankama.com/www/static.ankama.com/dofus/www/game/items/52/50719.w48h48.png","type":"Pierre précieuse","lvl":"10","quantity":"15"}},{"Corne de XLII":{"id":"15721","url":"https://www.dofus-touch.com/fr/mmorpg/encyclopedie/ressources/15721-corne-xlii","imgUrl":"https://s.ankama.com/www/static.ankama.com/dofus/www/game/items/52/15901.w48h48.png","type":"Os","lvl":"170","quantity":"13"}},{"Cheveux de Tal Kasha":{"id":"18542","url":"https://www.dofus-touch.com/fr/mmorpg/encyclopedie/ressources/18542-cheveux-tal-kasha","imgUrl":"https://s.ankama.com/www/static.ankama.com/dofus/www/game/items/52/54711.w48h48.png","type":"Poil","lvl":"200","quantity":"10"}},{"Vertèbre de Trépavois":{"id":"19400","url":"https://www.dofus-touch.com/fr/mmorpg/encyclopedie/ressources/19400-vertebre-trepavois","imgUrl":"https://s.ankama.com/www/static.ankama.com/dofus/www/game/items/52/47862.w48h48.png","type":"Os","lvl":"200","quantity":"82"}},{"Langue de Hacharné":{"id":"19401","url":"https://www.dofus-touch.com/fr/mmorpg/encyclopedie/ressources/19401-langue-hacharne","imgUrl":"https://s.ankama.com/www/static.ankama.com/dofus/www/game/items/52/164145.w48h48.png","type":"Ressources diverses","lvl":"200","quantity":"85"}},{"Cervelle de Solar":{"id":"19404","url":"https://www.dofus-touch.com/fr/mmorpg/encyclopedie/ressources/19404-cervelle-solar","imgUrl":"https://s.ankama.com/www/static.ankama.com/dofus/www/game/items/52/182019.w48h48.png","type":"Ressources diverses","lvl":"200","quantity":"7"}},{"Sang de Calciné":{"id":"19405","url":"https://www.dofus-touch.com/fr/mmorpg/encyclopedie/ressources/19405-sang-calcine","imgUrl":"https://s.ankama.com/www/static.ankama.com/dofus/www/game/items/52/12771.w48h48.png","type":"Ressources diverses","lvl":"200","quantity":"10"}}],"setId":453}