{"_id":19601,"name":"Cape de Crânonier","lvl":"200","type":"Cape","imgUrl":"https://s.ankama.com/www/static.ankama.com/dofus/www/game/items/200/17401.png","url":"https://www.dofus.com/fr/mmorpg/encyclopedie/equipements/19601-cape-cranonier","description":"Cet amas indescriptible d'écume et de coraux en décomposition ne dégage étrangement aucune odeur nauséabonde ; fait suffisamment surprenant dans le monde des Douze pour être mentionné.","stats":[{"Vitalité":{"from":"351","to":"400"}},{"Agilité":{"from":"41","to":"60"}},{"Résistance Poussée":{"from":"26","to":"35"}},{"Sagesse":{"from":"31","to":"40"}},{"Dommages Air":{"from":"16","to":"20"}},{"% Résistance Terre":{"from":"7","to":"10"}},{"% Résistance Eau":{"from":"7","to":"10"}},{"Esquive PA":{"from":"11","to":"15"}},{"% Critique":{"from":"3","to":"4"}}],"condition":[],"recipe":[{"Galet brasillant":{"id":"12740","url":"https://www.dofus-touch.com/fr/mmorpg/encyclopedie/ressources/12740-galet-brasillant","imgUrl":"https://s.ankama.com/www/static.ankama.com/dofus/www/game/items/52/15289.w48h48.png","type":"Galet","lvl":"150","quantity":"3"}},{"Corne d'Ombre":{"id":"14928","url":"https://www.dofus-touch.com/fr/mmorpg/encyclopedie/ressources/14928-corne-ombre","imgUrl":"https://s.ankama.com/www/static.ankama.com/dofus/www/game/items/52/47833.w48h48.png","type":"Os","lvl":"190","quantity":"10"}},{"Tourmaline":{"id":"15271","url":"https://www.dofus-touch.com/fr/mmorpg/encyclopedie/ressources/15271-tourmaline","imgUrl":"https://s.ankama.com/www/static.ankama.com/dofus/www/game/items/52/50719.w48h48.png","type":"Pierre précieuse","lvl":"10","quantity":"15"}},{"Poil de Meno":{"id":"17976","url":"https://www.dofus-touch.com/fr/mmorpg/encyclopedie/ressources/17976-poil-meno","imgUrl":"https://s.ankama.com/www/static.ankama.com/dofus/www/game/items/52/54707.w48h48.png","type":"Poil","lvl":"200","quantity":"11"}},{"Chair de Zombruth":{"id":"19406","url":"https://www.dofus-touch.com/fr/mmorpg/encyclopedie/ressources/19406-chair-zombruth","imgUrl":"https://s.ankama.com/www/static.ankama.com/dofus/www/game/items/52/111755.w48h48.png","type":"Ressources diverses","lvl":"200","quantity":"13"}},{"Aquarakne de Crânonier":{"id":"19409","url":"https://www.dofus-touch.com/fr/mmorpg/encyclopedie/ressources/19409-aquarakne-cranonier","imgUrl":"https://s.ankama.com/www/static.ankama.com/dofus/www/game/items/52/111754.w48h48.png","type":"Coquille","lvl":"200","quantity":"85"}},{"Queue de Bethel Akarna":{"id":"19411","url":"https://www.dofus-touch.com/fr/mmorpg/encyclopedie/ressources/19411-queue-bethel-akarna","imgUrl":"https://s.ankama.com/www/static.ankama.com/dofus/www/game/items/52/65772.w48h48.png","type":"Queue","lvl":"200","quantity":"11"}},{"Coquille de Submergé":{"id":"19412","url":"https://www.dofus-touch.com/fr/mmorpg/encyclopedie/ressources/19412-coquille-submerge","imgUrl":"https://s.ankama.com/www/static.ankama.com/dofus/www/game/items/52/111756.w48h48.png","type":"Coquille","lvl":"200","quantity":"10"}}],"setId":455}