{"_id":8217,"name":"Amulette du Piou Jaune","lvl":"12","type":"Amulette","imgUrl":"https://s.ankama.com/www/static.ankama.com/dofus/www/game/items/200/1104.png","url":"https://www.dofus.com/fr/mmorpg/encyclopedie/equipements/8217-amulette-piou-jaune","description":"Cette amulette semble avoir été confectionnée à partir d'une petite tête de Piou desséchée. La coquetterie n'a aucune limite.","stats":[{"Sagesse":{"from":"7","to":"10"}},{"Dommages Terre":{"from":"1"}}],"condition":[],"recipe":[{"Bave de Bouftou":{"id":"385","url":"https://www.dofus-touch.com/fr/mmorpg/encyclopedie/ressources/385-bave-bouftou","imgUrl":"https://s.ankama.com/www/static.ankama.com/dofus/www/game/items/52/15057.w48h48.png","type":"Ressources diverses","lvl":"7","quantity":"3"}},{"Plume de Piou Jaune":{"id":"6902","url":"https://www.dofus-touch.com/fr/mmorpg/encyclopedie/ressources/6902-plume-piou-jaune","imgUrl":"https://s.ankama.com/www/static.ankama.com/dofus/www/game/items/52/53118.w48h48.png","type":"Plume","lvl":"13","quantity":"3"}}],"setId":72}