{"_id":1501,"name":"Alliance","lvl":"1","type":"Anneau","imgUrl":"https://s.ankama.com/www/static.ankama.com/dofus/www/game/items/200/9027.png","url":"https://www.dofus.com/fr/mmorpg/encyclopedie/equipements/1501-alliance","description":"Cette alliance symbolise l'union entre deux âmes follement amoureuses l'une de l'autre. Inutile de conter fleurette caché derrière les buissons, cette fois c'est pour de bon, vous allez pouvoir vous afficher sans scrupules.","stats":[],"condition":[],"recipe":[],"setId":0}