{"_id":2485,"name":"Végacoiffe","lvl":"40","type":"Chapeau","imgUrl":"https://s.ankama.com/www/static.ankama.com/dofus/www/game/items/200/16045.png","url":"https://www.dofus.com/fr/mmorpg/encyclopedie/equipements/2485-vegacoiffe","description":"Le top du top de la mode, mais uniquement au nord-est d'Amakna.","stats":[{"Vitalité":{"from":"41","to":"50"}},{"Agilité":{"from":"31","to":"40"}},{"Prospection":{"from":"7","to":"10"}},{"Dommages Air":{"from":"2"}}],"condition":[],"recipe":[{"Ebonite":{"id":"746","url":"https://www.dofus-touch.com/fr/mmorpg/encyclopedie/ressources/746-ebonite","imgUrl":"https://s.ankama.com/www/static.ankama.com/dofus/www/game/items/52/40658.w48h48.png","type":"Alliage","lvl":"40","quantity":"2"}},{"Souris verte":{"id":"1771","url":"https://www.dofus-touch.com/fr/mmorpg/encyclopedie/ressources/1771-souris-verte","imgUrl":"https://s.ankama.com/www/static.ankama.com/dofus/www/game/items/52/15932.w48h48.png","type":"Ressources diverses","lvl":"56","quantity":"12"}},{"Petite Perle Dorée":{"id":"2328","url":"https://www.dofus-touch.com/fr/mmorpg/encyclopedie/ressources/2328-petite-perle-doree","imgUrl":"https://s.ankama.com/www/static.ankama.com/dofus/www/game/items/52/15483.w48h48.png","type":"Ressources diverses","lvl":"50","quantity":"10"}},{"Peau de Larve Champêtre":{"id":"2507","url":"https://www.dofus-touch.com/fr/mmorpg/encyclopedie/ressources/2507-peau-larve-champetre","imgUrl":"https://s.ankama.com/www/static.ankama.com/dofus/www/game/items/52/59652.w48h48.png","type":"Peau","lvl":"56","quantity":"1"}}],"setId":10}