{"_id":703,"name":"Dora","lvl":"36","type":"Chapeau","imgUrl":"https://s.ankama.com/www/static.ankama.com/dofus/www/game/items/200/16009.png","url":"https://www.dofus.com/fr/mmorpg/encyclopedie/equipements/703-dora","description":"Ce chapeau, en forme de corbeille à fruits en osier renversée, est en fait une corbeille à fruits renversée magique. Ce qui ne manquera pas d'impressionner votre entourage, surtout s'il est composé d'apprentis Bworks Mages.","stats":[{"Force":{"from":"41","to":"50"}},{"Intelligence":{"from":"41","to":"50"}},{"Agilité":{"from":"-25"}},{"Chance":{"from":"-25"}}],"condition":[],"recipe":[{"Laine du Chef de Guerre Bouftou":{"id":"882","url":"https://www.dofus-touch.com/fr/mmorpg/encyclopedie/ressources/882-laine-chef-guerre-bouftou","imgUrl":"https://s.ankama.com/www/static.ankama.com/dofus/www/game/items/52/57209.w48h48.png","type":"Laine","lvl":"29","quantity":"4"}},{"Cuir de Bouftou Noir":{"id":"884","url":"https://www.dofus-touch.com/fr/mmorpg/encyclopedie/ressources/884-cuir-bouftou-noir","imgUrl":"https://s.ankama.com/www/static.ankama.com/dofus/www/game/items/52/56016.w48h48.png","type":"Cuir","lvl":"26","quantity":"1"}},{"Feuille de Rose Obscure":{"id":"2318","url":"https://www.dofus-touch.com/fr/mmorpg/encyclopedie/ressources/2318-feuille-rose-obscure","imgUrl":"https://s.ankama.com/www/static.ankama.com/dofus/www/game/items/52/25152.w48h48.png","type":"Plante","lvl":"23","quantity":"1"}}],"setId":0}