{"_id":18621,"name":"Chapeau Devin","lvl":"40","type":"Chapeau","imgUrl":"https://s.ankama.com/www/static.ankama.com/dofus/www/game/items/200/16514.png","url":"https://www.dofus.com/fr/mmorpg/encyclopedie/equipements/18621-chapeau-devin","description":"On raconte qu'une fois affublés de ce chapeau, certains vieux Ouginaks parviennent à prédire l'évolution du climat dans les dix prochaines secondes.","stats":[{"Réduit de le délai de relance du sort Proie":{"from":"1"}},{"Augmente la portée du sort Molosse de 1":{"from":"1"}},{"Augmente la portée du sort Cubitus de 3":{"from":"3"}},{"Augmente les dégâts de base du sort Carcasse de 5":{"from":"5"}},{"Augmente de le nombre de lancer maximal par tour du sort Gibier":{"from":"1"}},{"Désactive la ligne de vue du sort Mâchoire":{}},{"Dommages sur le sort Calcaneus":{"from":"15"}},{"Désactive la ligne de vue du sort Dépouille":{}}],"condition":[],"recipe":[{"Corne de Dragoeuf Guerrier":{"id":"8363","url":"https://www.dofus-touch.com/fr/mmorpg/encyclopedie/ressources/8363-corne-dragoeuf-guerrier","imgUrl":"https://s.ankama.com/www/static.ankama.com/dofus/www/game/items/52/47651.w48h48.png","type":"Os","lvl":"110","quantity":"1"}},{"Pince de Crustorail":{"id":"8744","url":"https://www.dofus-touch.com/fr/mmorpg/encyclopedie/ressources/8744-pince-crustorail","imgUrl":"https://s.ankama.com/www/static.ankama.com/dofus/www/game/items/52/47017.w48h48.png","type":"Os","lvl":"42","quantity":"10"}},{"Pétale Morito":{"id":"8748","url":"https://www.dofus-touch.com/fr/mmorpg/encyclopedie/ressources/8748-petale-morito","imgUrl":"https://s.ankama.com/www/static.ankama.com/dofus/www/game/items/52/35006.w48h48.png","type":"Fleur","lvl":"43","quantity":"2"}},{"Bulbe Morito":{"id":"8752","url":"https://www.dofus-touch.com/fr/mmorpg/encyclopedie/ressources/8752-bulbe-morito","imgUrl":"https://s.ankama.com/www/static.ankama.com/dofus/www/game/items/52/36005.w48h48.png","type":"Plante","lvl":"43","quantity":"10"}},{"Étoffe Corailleuse":{"id":"8994","url":"https://www.dofus-touch.com/fr/mmorpg/encyclopedie/ressources/8994-etoffe-corailleuse","imgUrl":"https://s.ankama.com/www/static.ankama.com/dofus/www/game/items/52/55728.w48h48.png","type":"Étoffe","lvl":"50","quantity":"1"}}],"setId":430}