{"_id":2070,"name":"Shako","lvl":"34","type":"Chapeau","imgUrl":"https://s.ankama.com/www/static.ankama.com/dofus/www/game/items/200/16058.png","url":"https://www.dofus.com/fr/mmorpg/encyclopedie/equipements/2070-shako","description":"Ce casque en os a longtemps séjourné dans les poches d'un Kanigrou. Usé, rayé, il garde tout de même de belles propriétés.","stats":[{"Vitalité":{"from":"41","to":"50"}},{"Force":{"from":"-10"}},{"Intelligence":{"from":"41","to":"50"}},{"Dommages Feu":{"from":"3"}},{"Dommages Terre":{"from":"-3"}}],"condition":[],"recipe":[{"Noisette":{"id":"394","url":"https://www.dofus-touch.com/fr/mmorpg/encyclopedie/ressources/394-noisette","imgUrl":"https://s.ankama.com/www/static.ankama.com/dofus/www/game/items/52/58066.w48h48.png","type":"Graine","lvl":"26","quantity":"5"}},{"Pic du Prespic":{"id":"407","url":"https://www.dofus-touch.com/fr/mmorpg/encyclopedie/ressources/407-pic-prespic","imgUrl":"https://s.ankama.com/www/static.ankama.com/dofus/www/game/items/52/47134.w48h48.png","type":"Os","lvl":"26","quantity":"4"}},{"Œil de Ramane Strubien":{"id":"2453","url":"https://www.dofus-touch.com/fr/mmorpg/encyclopedie/ressources/2453-oeil-ramane-strubien","imgUrl":"https://s.ankama.com/www/static.ankama.com/dofus/www/game/items/52/25158.w48h48.png","type":"Œil","lvl":"26","quantity":"1"}}],"setId":0}