{"_id":12036,"name":"Botte de Kalkanéus","lvl":"39","type":"Bottes","imgUrl":"https://s.ankama.com/www/static.ankama.com/dofus/www/game/items/200/11196.png","url":"https://www.dofus.com/fr/mmorpg/encyclopedie/equipements/12036-botte-kalkaneus","description":"Kalkanéus ayant une jambe de bois, il n'a qu'une botte. Il vous suffit donc de la porter, seule, pour adopter la même démarche que lui, sans même avoir à l'incarner !","stats":[{"Sagesse":{"from":"7","to":"10"}},{"Portée":{"from":"1"}},{"Dommages Neutre":{"from":"4","to":"5"}},{"Résistance Poussée":{"from":"4","to":"5"}}],"condition":[],"recipe":[{"Défense du Sanglier":{"id":"387","url":"https://www.dofus-touch.com/fr/mmorpg/encyclopedie/ressources/387-defense-sanglier","imgUrl":"https://s.ankama.com/www/static.ankama.com/dofus/www/game/items/52/47059.w48h48.png","type":"Os","lvl":"24","quantity":"4"}},{"Cuir de Bouftou Noir":{"id":"884","url":"https://www.dofus-touch.com/fr/mmorpg/encyclopedie/ressources/884-cuir-bouftou-noir","imgUrl":"https://s.ankama.com/www/static.ankama.com/dofus/www/game/items/52/56016.w48h48.png","type":"Cuir","lvl":"26","quantity":"1"}},{"Crocs de Rats":{"id":"2322","url":"https://www.dofus-touch.com/fr/mmorpg/encyclopedie/ressources/2322-crocs-rats","imgUrl":"https://s.ankama.com/www/static.ankama.com/dofus/www/game/items/52/47464.w48h48.png","type":"Os","lvl":"26","quantity":"5"}}],"setId":201}