{"_id":15700,"name":"Protopagne","lvl":"200","type":"Ceinture","imgUrl":"https://s.ankama.com/www/static.ankama.com/dofus/www/game/items/200/10280.png","url":"https://www.dofus.com/fr/mmorpg/encyclopedie/equipements/15700-protopagne","description":"Ce pagne translucide est très apprécié des exhibitionnistes : sans les faire apparaître totalement nus, il ne cache absolument rien d’essentiel.","stats":[{"Vitalité":{"from":"351","to":"400"}},{"Résistance Critiques":{"from":"21","to":"25"}},{"Sagesse":{"from":"31","to":"50"}},{"Tacle":{"from":"-15"}},{"% Résistance Terre":{"from":"7","to":"10"}},{"% Résistance Feu":{"from":"7","to":"10"}},{"Esquive PM":{"from":"7","to":"10"}},{"Esquive PA":{"from":"7","to":"10"}},{"Invocations":{"from":"1"}},{"PM":{"from":"1"}}],"condition":["PA < 12"],"recipe":[{"Ongle du Bworker":{"id":"13157","url":"https://www.dofus-touch.com/fr/mmorpg/encyclopedie/ressources/13157-ongle-bworker","imgUrl":"https://s.ankama.com/www/static.ankama.com/dofus/www/game/items/52/47695.w48h48.png","type":"Os","lvl":"180","quantity":"10"}},{"Poil d'aisselle de Missiz Frizz":{"id":"13935","url":"https://www.dofus-touch.com/fr/mmorpg/encyclopedie/ressources/13935-poil-aisselle-missiz-frizz","imgUrl":"https://s.ankama.com/www/static.ankama.com/dofus/www/game/items/52/54691.w48h48.png","type":"Poil","lvl":"200","quantity":"12"}},{"Racine cristalline":{"id":"14141","url":"https://www.dofus-touch.com/fr/mmorpg/encyclopedie/ressources/14141-racine-cristalline","imgUrl":"https://s.ankama.com/www/static.ankama.com/dofus/www/game/items/52/98671.w48h48.png","type":"Racine","lvl":"200","quantity":"1"}},{"Tourmaline":{"id":"15271","url":"https://www.dofus-touch.com/fr/mmorpg/encyclopedie/ressources/15271-tourmaline","imgUrl":"https://s.ankama.com/www/static.ankama.com/dofus/www/game/items/52/50719.w48h48.png","type":"Pierre précieuse","lvl":"10","quantity":"15"}},{"Antenne de Bacterrib":{"id":"15686","url":"https://www.dofus-touch.com/fr/mmorpg/encyclopedie/ressources/15686-antenne-bacterrib","imgUrl":"https://s.ankama.com/www/static.ankama.com/dofus/www/game/items/52/164046.w48h48.png","type":"Ressources diverses","lvl":"200","quantity":"41"}},{"Peau de Pataugerme":{"id":"15688","url":"https://www.dofus-touch.com/fr/mmorpg/encyclopedie/ressources/15688-peau-pataugerme","imgUrl":"https://s.ankama.com/www/static.ankama.com/dofus/www/game/items/52/59647.w48h48.png","type":"Peau","lvl":"200","quantity":"19"}},{"Noyau de Protozorreur":{"id":"15689","url":"https://www.dofus-touch.com/fr/mmorpg/encyclopedie/ressources/15689-noyau-protozorreur","imgUrl":"https://s.ankama.com/www/static.ankama.com/dofus/www/game/items/52/164047.w48h48.png","type":"Ressources diverses","lvl":"200","quantity":"8"}},{"Sel de Baleine":{"id":"15691","url":"https://www.dofus-touch.com/fr/mmorpg/encyclopedie/ressources/15691-sel-baleine","imgUrl":"https://s.ankama.com/www/static.ankama.com/dofus/www/game/items/52/164045.w48h48.png","type":"Poudre","lvl":"200","quantity":"10"}}],"setId":0}